java_manifest.py
java_manifest-1.0.0.dist-info/WHEEL
java_manifest-1.0.0.dist-info/METADATA
java_manifest-1.0.0.dist-info/RECORD
