Metadata-Version: 2.1
Name: java-manifest
Version: 1.0.0
Summary: Encode/decode Java's META-INF/MANIFEST.MF in Python
Home-page: https://github.com/elihunter173/java-manifest-py
Keywords: java,jar,manifest
Author: Eli W. Hunter
Author-email: elihunter173@gmail.com
Requires-Python: >=3.6,<4.0
Classifier: Programming Language :: Python :: 3
Classifier: Programming Language :: Python :: 3.6
Classifier: Programming Language :: Python :: 3.7
Classifier: Programming Language :: Python :: 3.8
